dapper/README.md
dapper/__init__.py
dapper/dpr_config.py
dapper/dpr_config.yaml
dapper/stats.py
dapper/stats_etc.md
dapper/xp_launch.py
dapper/xp_process.py
dapper/da_methods/README.md
dapper/da_methods/__init__.py
dapper/da_methods/baseline.py
dapper/da_methods/ensemble.py
dapper/da_methods/extended.py
dapper/da_methods/other.py
dapper/da_methods/particle.py
dapper/da_methods/variational.py
dapper/mods/README.md
dapper/mods/__init__.py
dapper/mods/explore_props.py
dapper/mods/integration.py
dapper/mods/utils.py
dapper/mods/DoublePendulum/__init__.py
dapper/mods/DoublePendulum/demo.py
dapper/mods/DoublePendulum/settings101.py
dapper/mods/Id/__init__.py
dapper/mods/Ikeda/__init__.py
dapper/mods/Ikeda/demo.py
dapper/mods/Ikeda/some_settings_01.py
dapper/mods/KS/__init__.py
dapper/mods/KS/bocquet2019.py
dapper/mods/KS/compare_schemes.py
dapper/mods/KS/demo.py
dapper/mods/LA/__init__.py
dapper/mods/LA/demo.py
dapper/mods/LA/evensen2009.py
dapper/mods/LA/raanes2015.py
dapper/mods/LA/small.py
dapper/mods/Lorenz05/__init__.py
dapper/mods/Lorenz05/demo.py
dapper/mods/Lorenz05/settings01.py
dapper/mods/Lorenz63/__init__.py
dapper/mods/Lorenz63/anderson2010rhf.py
dapper/mods/Lorenz63/bocquet2012.py
dapper/mods/Lorenz63/demo.py
dapper/mods/Lorenz63/extras.py
dapper/mods/Lorenz63/mandel2016.py
dapper/mods/Lorenz63/ramgraber2022.py
dapper/mods/Lorenz63/sakov2012.py
dapper/mods/Lorenz63/wiljes2017.py
dapper/mods/Lorenz84/__init__.py
dapper/mods/Lorenz84/demo.py
dapper/mods/Lorenz84/harder.py
dapper/mods/Lorenz84/pajonk2012.py
dapper/mods/Lorenz96/__init__.py
dapper/mods/Lorenz96/anderson2009.py
dapper/mods/Lorenz96/bocquet2010.py
dapper/mods/Lorenz96/bocquet2010_m40.py
dapper/mods/Lorenz96/bocquet2015loc.py
dapper/mods/Lorenz96/demo.py
dapper/mods/Lorenz96/extras.py
dapper/mods/Lorenz96/frei2013bridging.py
dapper/mods/Lorenz96/hoteit2015.py
dapper/mods/Lorenz96/miyoshi2011.py
dapper/mods/Lorenz96/pinheiro2019.py
dapper/mods/Lorenz96/raanes2016.py
dapper-1.7.3.dist-info/licenses/LICENCE.txt
dapper-1.7.3.dist-info/METADATA
dapper-1.7.3.dist-info/WHEEL
dapper-1.7.3.dist-info/top_level.txt
dapper-1.7.3.dist-info/RECORD
